py.typed
codat_commerce/__init__.py
codat_commerce/_hooks/__init__.py
codat_commerce/_hooks/registration.py
codat_commerce/_hooks/sdkhooks.py
codat_commerce/_hooks/types.py
codat_commerce/basesdk.py
codat_commerce/company_info_sdk.py
codat_commerce/customers_sdk.py
codat_commerce/disputes_sdk.py
codat_commerce/httpclient.py
codat_commerce/locations_sdk.py
codat_commerce/models/__init__.py
codat_commerce/models/accountbalance.py
codat_commerce/models/address.py
codat_commerce/models/commerceaddresstype.py
codat_commerce/models/commercecustomerref.py
codat_commerce/models/companyinfo.py
codat_commerce/models/customer.py
codat_commerce/models/customers.py
codat_commerce/models/dispute.py
codat_commerce/models/disputes.py
codat_commerce/models/disputestatus.py
codat_commerce/models/errormessage.py
codat_commerce/models/errorvalidation.py
codat_commerce/models/errorvalidationitem.py
codat_commerce/models/get_company_infoop.py
codat_commerce/models/get_customerop.py
codat_commerce/models/get_disputeop.py
codat_commerce/models/get_locationop.py
codat_commerce/models/get_orderop.py
codat_commerce/models/get_payment_methodop.py
codat_commerce/models/get_paymentop.py
codat_commerce/models/get_product_categoryop.py
codat_commerce/models/get_productop.py
codat_commerce/models/get_tax_componentop.py
codat_commerce/models/get_transactionop.py
codat_commerce/models/halref.py
codat_commerce/models/links.py
codat_commerce/models/list_customersop.py
codat_commerce/models/list_disputesop.py
codat_commerce/models/list_locationsop.py
codat_commerce/models/list_ordersop.py
codat_commerce/models/list_payment_methodsop.py
codat_commerce/models/list_paymentsop.py
codat_commerce/models/list_product_categoriesop.py
codat_commerce/models/list_productsop.py
codat_commerce/models/list_tax_componentsop.py
codat_commerce/models/list_transactionsop.py
codat_commerce/models/location.py
codat_commerce/models/locationref.py
codat_commerce/models/locations.py
codat_commerce/models/order.py
codat_commerce-0.35.0.dist-info/METADATA
codat_commerce-0.35.0.dist-info/WHEEL
codat_commerce-0.35.0.dist-info/RECORD
